CHANGELOG.md
MANIFEST.in
README.md
setup.py
SLC/__init__.py
SLC.egg-info/PKG-INFO
SLC.egg-info/SOURCES.txt
SLC.egg-info/dependency_links.txt
SLC.egg-info/requires.txt
SLC.egg-info/top_level.txt
SLC/SLshorcuts/__init__.py