Metadata-Version: 2.1
Name: SLC
Version: 0.3.3
Summary: A tool that allows you to connect to and run SQL commands to an SQLite3 database easily.
Home-page: https://downloadSLC.jonathan2018.repl.co/dev/pr/downloads/files/SLC-0.3.2.tar.gz
Author: Jonathan Wang
Author-email: jonathanwang2018@gmail.com
License: UNKNOWN
Keywords: SQL,SQLite3,Database
Platform: UNKNOWN
Classifier: Development Status :: 5 - Production/Stable
Classifier: Intended Audience :: Information Technology
Classifier: Operating System :: OS Independent
Classifier: License :: OSI Approved :: MIT License
Classifier: Programming Language :: Python :: 3
Classifier: Natural Language :: English
